Metadata-Version: 2.1
Name: AudioAugmentation
Version: 0.10.0
Summary: Transformaciones de audios
Home-page: https://github.com/wisrovi/AudioAugmentation
Author: William Rodriguez
Author-email: wisrovi.rodriguez@gmail.com
License: GPLv3
Download-URL: http://chardet.feedparser.org/download/python3-chardet-1.0.1.tgz
Keywords: encoding,i18n,xml
Platform: UNKNOWN
Classifier: Programming Language :: Python
Classifier: Programming Language :: Python :: 3
Classifier: License :: OSI Approved :: GNU General Public License v3 (GPLv3)
Classifier: Operating System :: OS Independent
Classifier: Development Status :: 4 - Beta
Classifier: Intended Audience :: Developers
Classifier: Topic :: Software Development :: Libraries :: Python Modules
